alpha_utils/__init__.py
alpha_utils/function.cp310-win_amd64.pyd
alpha_utils/function.py
alpha_utils-2.2.2.dist-info/METADATA
alpha_utils-2.2.2.dist-info/WHEEL
alpha_utils-2.2.2.dist-info/top_level.txt
alpha_utils-2.2.2.dist-info/RECORD
