Metadata-Version: 2.1
Name: alpha_utils
Version: 2.2.2
Summary: alpha utils
Home-page: https://github.com/zengbaocheng-996/alpha_utils
Author: ZENGBAOCHENG
Author-email: 3180102361@zju.edu.cn
Classifier: Programming Language :: Python :: 3
Classifier: License :: OSI Approved :: MIT License
Classifier: Operating System :: OS Independent
Requires-Python: >=3.6
